ofxstatement_mt940-1.3.1-py3.10-nspkg.pth
ofxstatement/plugins/mt940.py
ofxstatement/plugins/statement.py
ofxstatement_mt940-1.3.1.dist-info/METADATA
ofxstatement_mt940-1.3.1.dist-info/WHEEL
ofxstatement_mt940-1.3.1.dist-info/entry_points.txt
ofxstatement_mt940-1.3.1.dist-info/namespace_packages.txt
ofxstatement_mt940-1.3.1.dist-info/top_level.txt
ofxstatement_mt940-1.3.1.dist-info/zip-safe
ofxstatement_mt940-1.3.1.dist-info/RECORD
