Metadata-Version: 2.1
Name: ofxstatement-mt940
Version: 1.3.1
Summary: OFXStatement plugin for financial institutions providing MT940 statements.
Home-page: https://github.com/gpaulissen/ofxstatement-mt940
Author: Gert-Jan Paulissen
Author-email: gert.jan.paulissen@gmail.com
License: GPLv3
Keywords: ofx,banking,statement,mt940
Platform: UNKNOWN
Classifier: Development Status :: 6 - Mature
Classifier: Programming Language :: Python :: 3
Classifier: Natural Language :: English
Classifier: Topic :: Office/Business :: Financial :: Accounting
Classifier: Topic :: Utilities
Classifier: Environment :: Console
Classifier: Operating System :: OS Independent
Classifier: License :: OSI Approved :: GNU General Public License v3 (GPLv3)
Requires-Dist: ofxstatement (>0.6.4)
Requires-Dist: mt-940 (>=4.19.0)
Provides-Extra: test
Requires-Dist: flake8 ; extra == 'test'
Requires-Dist: mypy ; extra == 'test'
Requires-Dist: pytest ; extra == 'test'
Requires-Dist: pytest-cache ; extra == 'test'
Requires-Dist: pytest-cover ; extra == 'test'
Requires-Dist: pytest-flakes ; extra == 'test'
Requires-Dist: pytest-pep8 ; extra == 'test'
Requires-Dist: pytest-pycodestyle ; extra == 'test'
Requires-Dist: pyyaml ; extra == 'test'
